errbot_rethinkdb_storage/__init__.py
errbot_rethinkdb_storage/rethinkdbstorage.plug
errbot_rethinkdb_storage/rethinkdbstorage.py
errbot_rethinkdb_storage-1.1.2.dist-info/DESCRIPTION.rst
errbot_rethinkdb_storage-1.1.2.dist-info/METADATA
errbot_rethinkdb_storage-1.1.2.dist-info/RECORD
errbot_rethinkdb_storage-1.1.2.dist-info/WHEEL
errbot_rethinkdb_storage-1.1.2.dist-info/metadata.json
errbot_rethinkdb_storage-1.1.2.dist-info/top_level.txt
