Metadata-Version: 2.0
Name: errbot-rethinkdb-storage
Version: 1.1.2
Summary: RethinkDB storage plugin for ErrBot
Home-page: https://gitlab.com/AnjiProject/errbot-rethinkdb-storage
Author: Bogdan Gladyshev
Author-email: siredvin.dark@gmail.com
License: MIT license
Keywords: errbot_rethinkdb_storage
Platform: UNKNOWN
Classifier: Development Status :: 5 - Production/Stable
Classifier: Intended Audience :: Developers
Classifier: License :: OSI Approved :: MIT License
Classifier: Natural Language :: English
Classifier: Programming Language :: Python :: 3.5
Classifier: Programming Language :: Python :: 3.6
Requires-Dist: errbot (>=5.1.0)
Requires-Dist: repool-forked (>=0.3)
